Workbook
Name AvgSalary: Inputs!$B$10
Name BaseRevenue: Inputs!$B$2
Name COGS_pct: Inputs!$B$5
Name DPO: Inputs!$B$14
Name DSI: Inputs!$B$13
Name DSO: Inputs!$B$12
Name Fixed_Opex: Inputs!$B$6
Name Headcount_Start: Inputs!$B$8
Name HiringRate: Inputs!$B$9
Name OpEx_Var_pct: Inputs!$B$7
Name PriceGrowth: Inputs!$B$4
Name Scenario_Table: Scenario_Table!$A$2:$E$4
Name ScenarioSelector: Inputs!$B$15
Name Seasonality: Inputs!$A$20:$L$20
Name TaxRate: Inputs!$B$11
Name VolumeGrowth: Inputs!$B$3

Sheet Inputs
A1: Driver Name | B1: Value | C1: Named Range
A2: Base Monthly Revenue | B2: 150000 | C2: BaseRevenue
A3: Volume Growth (Monthly) | B3: 0.02 | C3: VolumeGrowth
A4: Price Growth (Monthly) | B4: 0.005 | C4: PriceGrowth
A5: COGS % | B5: 0.4 | C5: COGS_pct
A6: Fixed OpEx (Monthly) | B6: 45000 | C6: Fixed_Opex
A7: OpEx Var % | B7: 0.1 | C7: OpEx_Var_pct
A8: Headcount Start | B8: 12 | C8: Headcount_Start
A9: Hiring Rate | B9: 0.2 | C9: HiringRate
A10: Average Salary | B10: 6000 | C10: AvgSalary
A11: Tax Rate | B11: 0.25 | C11: TaxRate
A12: DSO (Days Sales Outstanding) | B12: 45 | C12: DSO
A13: DSI (Days Sales Inventory) | B13: 30 | C13: DSI
A14: DPO (Days Payables Outstanding) | B14: 30 | C14: DPO
A15: Scenario Selector | B15: Base | C15: ScenarioSelector
A18: Seasonality Table
A19: 1 | B19: 2 | C19: 3 | D19: 4 | E19: 5 | F19: 6 | G19: 7 | H19: 8 | I19: 9 | J19: 10 | K19: 11 | L19: 12
A20: 0.85 | B20: 0.85 | C20: 0.9 | D20: 0.95 | E20: 1 | F20: 1.05 | G20: 1.1 | H20: 1.05 | I20: 1.1 | J20: 1.15 | K20: 1.2 | L20: 1.4

Sheet Scenario_Table
A1: Scenario | B1: Revenue_Mult | C1: COGS_Mult | D1: Volume_Growth_Adj | E1: Price_Growth_Adj
A2: Base | B2: 1 | C2: 1 | D2: 0 | E2: 0
A3: Best | B3: 1.15 | C3: 0.95 | D3: 0.01 | E3: 0.005
A4: Worst | B4: 0.85 | C4: 1.1 | D4: -0.01 | E4: -0.005

Sheet Engine
A1: Date | B1: MonthIdx | C1: Revenue | D1: COGS | E1: OpEx | F1: Payroll | G1: Headcount | H1: EBITDA | I1: Capex | J1: Depreciation | K1: EBIT | L1: Tax | M1: NetIncome
A2: 2025-01-01 | B2: =MONTH(A2) -> 0 | C2: =BaseRevenue * ((1 + VolumeGrowth + INDEX(Scenario_Table,MATCH(ScenarioSelector,INDEX(Scenario_Table,,1),0),4))^(ROW()-2)) * ((1 + PriceGrowth + INDEX(Scenario_Table,MATCH(ScenarioSelector,INDEX(Scenario_Table,,1),0),5))^(ROW()-2)) * INDEX(Seasonality, B2) * INDEX(Scenario_Table,MATCH(ScenarioSelector,INDEX(Scenario_Table,,1),0),2) -> 0 | D2: =C2 * COGS_pct * INDEX(Scenario_Table,MATCH(ScenarioSelector,INDEX(Scenario_Table,,1),0),3) -> 0 | E2: =Fixed_Opex + (C2 * OpEx_Var_pct) + F2 -> 0 | F2: =G2 * AvgSalary -> 0 | G2: =Headcount_Start + INT(HiringRate * (ROW()-2)) -> 0 | H2: =C2 - D2 - E2 -> 0 | I2: 0 | J2: 0 | K2: =H2 - J2 -> 0 | L2: =MAX(0, K2 * TaxRate) -> 0 | M2: =K2 - L2 -> 0
A3: 2025-02-01 | B3: =MONTH(A3) -> 0 | C3: =BaseRevenue * ((1 + VolumeGrowth + INDEX(Scenario_Table,MATCH(ScenarioSelector,INDEX(Scenario_Table,,1),0),4))^(ROW()-2)) * ((1 + PriceGrowth + INDEX(Scenario_Table,MATCH(ScenarioSelector,INDEX(Scenario_Table,,1),0),5))^(ROW()-2)) * INDEX(Seasonality, B3) * INDEX(Scenario_Table,MATCH(ScenarioSelector,INDEX(Scenario_Table,,1),0),2) -> 0 | D3: =C3 * COGS_pct * INDEX(Scenario_Table,MATCH(ScenarioSelector,INDEX(Scenario_Table,,1),0),3) -> 0 | E3: =Fixed_Opex + (C3 * OpEx_Var_pct) + F3 -> 0 | F3: =G3 * AvgSalary -> 0 | G3: =Headcount_Start + INT(HiringRate * (ROW()-2)) -> 0 | H3: =C3 - D3 - E3 -> 0 | I3: 0 | J3: 0 | K3: =H3 - J3 -> 0 | L3: =MAX(0, K3 * TaxRate) -> 0 | M3: =K3 - L3 -> 0
A4: 2025-03-01 | B4: =MONTH(A4) -> 0 | C4: =BaseRevenue * ((1 + VolumeGrowth + INDEX(Scenario_Table,MATCH(ScenarioSelector,INDEX(Scenario_Table,,1),0),4))^(ROW()-2)) * ((1 + PriceGrowth + INDEX(Scenario_Table,MATCH(ScenarioSelector,INDEX(Scenario_Table,,1),0),5))^(ROW()-2)) * INDEX(Seasonality, B4) * INDEX(Scenario_Table,MATCH(ScenarioSelector,INDEX(Scenario_Table,,1),0),2) -> 0 | D4: =C4 * COGS_pct * INDEX(Scenario_Table,MATCH(ScenarioSelector,INDEX(Scenario_Table,,1),0),3) -> 0 | E4: =Fixed_Opex + (C4 * OpEx_Var_pct) + F4 -> 0 | F4: =G4 * AvgSalary -> 0 | G4: =Headcount_Start + INT(HiringRate * (ROW()-2)) -> 0 | H4: =C4 - D4 - E4 -> 0 | I4: 50000 | J4: 833.33333 | K4: =H4 - J4 -> 0 | L4: =MAX(0, K4 * TaxRate) -> 0 | M4: =K4 - L4 -> 0
A5: 2025-04-01 | B5: =MONTH(A5) -> 0 | C5: =BaseRevenue * ((1 + VolumeGrowth + INDEX(Scenario_Table,MATCH(ScenarioSelector,INDEX(Scenario_Table,,1),0),4))^(ROW()-2)) * ((1 + PriceGrowth + INDEX(Scenario_Table,MATCH(ScenarioSelector,INDEX(Scenario_Table,,1),0),5))^(ROW()-2)) * INDEX(Seasonality, B5) * INDEX(Scenario_Table,MATCH(ScenarioSelector,INDEX(Scenario_Table,,1),0),2) -> 0 | D5: =C5 * COGS_pct * INDEX(Scenario_Table,MATCH(ScenarioSelector,INDEX(Scenario_Table,,1),0),3) -> 0 | E5: =Fixed_Opex + (C5 * OpEx_Var_pct) + F5 -> 0 | F5: =G5 * AvgSalary -> 0 | G5: =Headcount_Start + INT(HiringRate * (ROW()-2)) -> 0 | H5: =C5 - D5 - E5 -> 0 | I5: 0 | J5: 833.33333 | K5: =H5 - J5 -> 0 | L5: =MAX(0, K5 * TaxRate) -> 0 | M5: =K5 - L5 -> 0
A6: 2025-05-01 | B6: =MONTH(A6) -> 0 | C6: =BaseRevenue * ((1 + VolumeGrowth + INDEX(Scenario_Table,MATCH(ScenarioSelector,INDEX(Scenario_Table,,1),0),4))^(ROW()-2)) * ((1 + PriceGrowth + INDEX(Scenario_Table,MATCH(ScenarioSelector,INDEX(Scenario_Table,,1),0),5))^(ROW()-2)) * INDEX(Seasonality, B6) * INDEX(Scenario_Table,MATCH(ScenarioSelector,INDEX(Scenario_Table,,1),0),2) -> 0 | D6: =C6 * COGS_pct * INDEX(Scenario_Table,MATCH(ScenarioSelector,INDEX(Scenario_Table,,1),0),3) -> 0 | E6: =Fixed_Opex + (C6 * OpEx_Var_pct) + F6 -> 0 | F6: =G6 * AvgSalary -> 0 | G6: =Headcount_Start + INT(HiringRate * (ROW()-2)) -> 0 | H6: =C6 - D6 - E6 -> 0 | I6: 0 | J6: 833.33333 | K6: =H6 - J6 -> 0 | L6: =MAX(0, K6 * TaxRate) -> 0 | M6: =K6 - L6 -> 0
A7: 2025-06-01 | B7: =MONTH(A7) -> 0 | C7: =BaseRevenue * ((1 + VolumeGrowth + INDEX(Scenario_Table,MATCH(ScenarioSelector,INDEX(Scenario_Table,,1),0),4))^(ROW()-2)) * ((1 + PriceGrowth + INDEX(Scenario_Table,MATCH(ScenarioSelector,INDEX(Scenario_Table,,1),0),5))^(ROW()-2)) * INDEX(Seasonality, B7) * INDEX(Scenario_Table,MATCH(ScenarioSelector,INDEX(Scenario_Table,,1),0),2) -> 0 | D7: =C7 * COGS_pct * INDEX(Scenario_Table,MATCH(ScenarioSelector,INDEX(Scenario_Table,,1),0),3) -> 0 | E7: =Fixed_Opex + (C7 * OpEx_Var_pct) + F7 -> 0 | F7: =G7 * AvgSalary -> 0 | G7: =Headcount_Start + INT(HiringRate * (ROW()-2)) -> 0 | H7: =C7 - D7 - E7 -> 0 | I7: 0 | J7: 833.33333 | K7: =H7 - J7 -> 0 | L7: =MAX(0, K7 * TaxRate) -> 0 | M7: =K7 - L7 -> 0
A8: 2025-07-01 | B8: =MONTH(A8) -> 0 | C8: =BaseRevenue * ((1 + VolumeGrowth + INDEX(Scenario_Table,MATCH(ScenarioSelector,INDEX(Scenario_Table,,1),0),4))^(ROW()-2)) * ((1 + PriceGrowth + INDEX(Scenario_Table,MATCH(ScenarioSelector,INDEX(Scenario_Table,,1),0),5))^(ROW()-2)) * INDEX(Seasonality, B8) * INDEX(Scenario_Table,MATCH(ScenarioSelector,INDEX(Scenario_Table,,1),0),2) -> 0 | D8: =C8 * COGS_pct * INDEX(Scenario_Table,MATCH(ScenarioSelector,INDEX(Scenario_Table,,1),0),3) -> 0 | E8: =Fixed_Opex + (C8 * OpEx_Var_pct) + F8 -> 0 | F8: =G8 * AvgSalary -> 0 | G8: =Headcount_Start + INT(HiringRate * (ROW()-2)) -> 0 | H8: =C8 - D8 - E8 -> 0 | I8: 0 | J8: 833.33333 | K8: =H8 - J8 -> 0 | L8: =MAX(0, K8 * TaxRate) -> 0 | M8: =K8 - L8 -> 0
A9: 2025-08-01 | B9: =MONTH(A9) -> 0 | C9: =BaseRevenue * ((1 + VolumeGrowth + INDEX(Scenario_Table,MATCH(ScenarioSelector,INDEX(Scenario_Table,,1),0),4))^(ROW()-2)) * ((1 + PriceGrowth + INDEX(Scenario_Table,MATCH(ScenarioSelector,INDEX(Scenario_Table,,1),0),5))^(ROW()-2)) * INDEX(Seasonality, B9) * INDEX(Scenario_Table,MATCH(ScenarioSelector,INDEX(Scenario_Table,,1),0),2) -> 0 | D9: =C9 * COGS_pct * INDEX(Scenario_Table,MATCH(ScenarioSelector,INDEX(Scenario_Table,,1),0),3) -> 0 | E9: =Fixed_Opex + (C9 * OpEx_Var_pct) + F9 -> 0 | F9: =G9 * AvgSalary -> 0 | G9: =Headcount_Start + INT(HiringRate * (ROW()-2)) -> 0 | H9: =C9 - D9 - E9 -> 0 | I9: 0 | J9: 833.33333 | K9: =H9 - J9 -> 0 | L9: =MAX(0, K9 * TaxRate) -> 0 | M9: =K9 - L9 -> 0
A10: 2025-09-01 | B10: =MONTH(A10) -> 0 | C10: =BaseRevenue * ((1 + VolumeGrowth + INDEX(Scenario_Table,MATCH(ScenarioSelector,INDEX(Scenario_Table,,1),0),4))^(ROW()-2)) * ((1 + PriceGrowth + INDEX(Scenario_Table,MATCH(ScenarioSelector,INDEX(Scenario_Table,,1),0),5))^(ROW()-2)) * INDEX(Seasonality, B10) * INDEX(Scenario_Table,MATCH(ScenarioSelector,INDEX(Scenario_Table,,1),0),2) -> 0 | D10: =C10 * COGS_pct * INDEX(Scenario_Table,MATCH(ScenarioSelector,INDEX(Scenario_Table,,1),0),3) -> 0 | E10: =Fixed_Opex + (C10 * OpEx_Var_pct) + F10 -> 0 | F10: =G10 * AvgSalary -> 0 | G10: =Headcount_Start + INT(HiringRate * (ROW()-2)) -> 0 | H10: =C10 - D10 - E10 -> 0 | I10: 75000 | J10: 2083.3333 | K10: =H10 - J10 -> 0 | L10: =MAX(0, K10 * TaxRate) -> 0 | M10: =K10 - L10 -> 0
A11: 2025-10-01 | B11: =MONTH(A11) -> 0 | C11: =BaseRevenue * ((1 + VolumeGrowth + INDEX(Scenario_Table,MATCH(ScenarioSelector,INDEX(Scenario_Table,,1),0),4))^(ROW()-2)) * ((1 + PriceGrowth + INDEX(Scenario_Table,MATCH(ScenarioSelector,INDEX(Scenario_Table,,1),0),5))^(ROW()-2)) * INDEX(Seasonality, B11) * INDEX(Scenario_Table,MATCH(ScenarioSelector,INDEX(Scenario_Table,,1),0),2) -> 0 | D11: =C11 * COGS_pct * INDEX(Scenario_Table,MATCH(ScenarioSelector,INDEX(Scenario_Table,,1),0),3) -> 0 | E11: =Fixed_Opex + (C11 * OpEx_Var_pct) + F11 -> 0 | F11: =G11 * AvgSalary -> 0 | G11: =Headcount_Start + INT(HiringRate * (ROW()-2)) -> 0 | H11: =C11 - D11 - E11 -> 0 | I11: 0 | J11: 2083.3333 | K11: =H11 - J11 -> 0 | L11: =MAX(0, K11 * TaxRate) -> 0 | M11: =K11 - L11 -> 0
A12: 2025-11-01 | B12: =MONTH(A12) -> 0 | C12: =BaseRevenue * ((1 + VolumeGrowth + INDEX(Scenario_Table,MATCH(ScenarioSelector,INDEX(Scenario_Table,,1),0),4))^(ROW()-2)) * ((1 + PriceGrowth + INDEX(Scenario_Table,MATCH(ScenarioSelector,INDEX(Scenario_Table,,1),0),5))^(ROW()-2)) * INDEX(Seasonality, B12) * INDEX(Scenario_Table,MATCH(ScenarioSelector,INDEX(Scenario_Table,,1),0),2) -> 0 | D12: =C12 * COGS_pct * INDEX(Scenario_Table,MATCH(ScenarioSelector,INDEX(Scenario_Table,,1),0),3) -> 0 | E12: =Fixed_Opex + (C12 * OpEx_Var_pct) + F12 -> 0 | F12: =G12 * AvgSalary -> 0 | G12: =Headcount_Start + INT(HiringRate * (ROW()-2)) -> 0 | H12: =C12 - D12 - E12 -> 0 | I12: 0 | J12: 2083.3333 | K12: =H12 - J12 -> 0 | L12: =MAX(0, K12 * TaxRate) -> 0 | M12: =K12 - L12 -> 0
A13: 2025-12-01 | B13: =MONTH(A13) -> 0 | C13: =BaseRevenue * ((1 + VolumeGrowth + INDEX(Scenario_Table,MATCH(ScenarioSelector,INDEX(Scenario_Table,,1),0),4))^(ROW()-2)) * ((1 + PriceGrowth + INDEX(Scenario_Table,MATCH(ScenarioSelector,INDEX(Scenario_Table,,1),0),5))^(ROW()-2)) * INDEX(Seasonality, B13) * INDEX(Scenario_Table,MATCH(ScenarioSelector,INDEX(Scenario_Table,,1),0),2) -> 0 | D13: =C13 * COGS_pct * INDEX(Scenario_Table,MATCH(ScenarioSelector,INDEX(Scenario_Table,,1),0),3) -> 0 | E13: =Fixed_Opex + (C13 * OpEx_Var_pct) + F13 -> 0 | F13: =G13 * AvgSalary -> 0 | G13: =Headcount_Start + INT(HiringRate * (ROW()-2)) -> 0 | H13: =C13 - D13 - E13 -> 0 | I13: 0 | J13: 2083.3333 | K13: =H13 - J13 -> 0 | L13: =MAX(0, K13 * TaxRate) -> 0 | M13: =K13 - L13 -> 0
... A37: 2027-12-01 | B37: =MONTH(A37) -> 0 | C37: =BaseRevenue * ((1 + VolumeGrowth + INDEX(Scenario_Table,MATCH(ScenarioSelector,INDEX(Scenario_Table,,1),0),4))^(ROW()-2)) * ((1 + PriceGrowth + INDEX(Scenario_Table,MATCH(ScenarioSelector,INDEX(Scenario_Table,,1),0),5))^(ROW()-2)) * INDEX(Seasonality, B37) * INDEX(Scenario_Table,MATCH(ScenarioSelector,INDEX(Scenario_Table,,1),0),2) -> 0 | D37: =C37 * COGS_pct * INDEX(Scenario_Table,MATCH(ScenarioSelector,INDEX(Scenario_Table,,1),0),3) -> 0 | E37: =Fixed_Opex + (C37 * OpEx_Var_pct) + F37 -> 0 | F37: =G37 * AvgSalary -> 0 | G37: =Headcount_Start + INT(HiringRate * (ROW()-2)) -> 0 | H37: =C37 - D37 - E37 -> 0 | I37: 0 | J37: 4583.3333 | K37: =H37 - J37 -> 0 | L37: =MAX(0, K37 * TaxRate) -> 0 | M37: =K37 - L37 -> 0

Sheet Working_Capital
A1: Date | B1: Revenue | C1: COGS | D1: OpEx | E1: AR | F1: Inventory | G1: AP | H1: NWC | I1: Delta_NWC | J1: NetIncome | K1: Depreciation | L1: Capex | M1: CashFlow | N1: CashBalance
A2: 2025-01-01 | B2: =Engine!C2 -> 0 | C2: =Engine!D2 -> 0 | D2: =Engine!E2 -> 0 | E2: =B2 * DSO / 30 -> 0 | F2: =C2 * DSI / 30 -> 0 | G2: =(C2 + D2) * DPO / 30 -> 0 | H2: =E2 + F2 - G2 -> 0 | I2: =H2 - 0 -> 0 | J2: =Engine!M2 -> 0 | K2: =Engine!J2 -> 0 | L2: =Engine!I2 -> 0 | M2: =J2 + K2 - I2 - L2 -> 0 | N2: =500000 + M2 -> 0
A3: 2025-02-01 | B3: =Engine!C3 -> 0 | C3: =Engine!D3 -> 0 | D3: =Engine!E3 -> 0 | E3: =B3 * DSO / 30 -> 0 | F3: =C3 * DSI / 30 -> 0 | G3: =(C3 + D3) * DPO / 30 -> 0 | H3: =E3 + F3 - G3 -> 0 | I3: =H3 - H2 -> 0 | J3: =Engine!M3 -> 0 | K3: =Engine!J3 -> 0 | L3: =Engine!I3 -> 0 | M3: =J3 + K3 - I3 - L3 -> 0 | N3: =N2 + M3 -> 0
A4: 2025-03-01 | B4: =Engine!C4 -> 0 | C4: =Engine!D4 -> 0 | D4: =Engine!E4 -> 0 | E4: =B4 * DSO / 30 -> 0 | F4: =C4 * DSI / 30 -> 0 | G4: =(C4 + D4) * DPO / 30 -> 0 | H4: =E4 + F4 - G4 -> 0 | I4: =H4 - H3 -> 0 | J4: =Engine!M4 -> 0 | K4: =Engine!J4 -> 0 | L4: =Engine!I4 -> 0 | M4: =J4 + K4 - I4 - L4 -> 0 | N4: =N3 + M4 -> 0
A5: 2025-04-01 | B5: =Engine!C5 -> 0 | C5: =Engine!D5 -> 0 | D5: =Engine!E5 -> 0 | E5: =B5 * DSO / 30 -> 0 | F5: =C5 * DSI / 30 -> 0 | G5: =(C5 + D5) * DPO / 30 -> 0 | H5: =E5 + F5 - G5 -> 0 | I5: =H5 - H4 -> 0 | J5: =Engine!M5 -> 0 | K5: =Engine!J5 -> 0 | L5: =Engine!I5 -> 0 | M5: =J5 + K5 - I5 - L5 -> 0 | N5: =N4 + M5 -> 0
A6: 2025-05-01 | B6: =Engine!C6 -> 0 | C6: =Engine!D6 -> 0 | D6: =Engine!E6 -> 0 | E6: =B6 * DSO / 30 -> 0 | F6: =C6 * DSI / 30 -> 0 | G6: =(C6 + D6) * DPO / 30 -> 0 | H6: =E6 + F6 - G6 -> 0 | I6: =H6 - H5 -> 0 | J6: =Engine!M6 -> 0 | K6: =Engine!J6 -> 0 | L6: =Engine!I6 -> 0 | M6: =J6 + K6 - I6 - L6 -> 0 | N6: =N5 + M6 -> 0
A7: 2025-06-01 | B7: =Engine!C7 -> 0 | C7: =Engine!D7 -> 0 | D7: =Engine!E7 -> 0 | E7: =B7 * DSO / 30 -> 0 | F7: =C7 * DSI / 30 -> 0 | G7: =(C7 + D7) * DPO / 30 -> 0 | H7: =E7 + F7 - G7 -> 0 | I7: =H7 - H6 -> 0 | J7: =Engine!M7 -> 0 | K7: =Engine!J7 -> 0 | L7: =Engine!I7 -> 0 | M7: =J7 + K7 - I7 - L7 -> 0 | N7: =N6 + M7 -> 0
A8: 2025-07-01 | B8: =Engine!C8 -> 0 | C8: =Engine!D8 -> 0 | D8: =Engine!E8 -> 0 | E8: =B8 * DSO / 30 -> 0 | F8: =C8 * DSI / 30 -> 0 | G8: =(C8 + D8) * DPO / 30 -> 0 | H8: =E8 + F8 - G8 -> 0 | I8: =H8 - H7 -> 0 | J8: =Engine!M8 -> 0 | K8: =Engine!J8 -> 0 | L8: =Engine!I8 -> 0 | M8: =J8 + K8 - I8 - L8 -> 0 | N8: =N7 + M8 -> 0
A9: 2025-08-01 | B9: =Engine!C9 -> 0 | C9: =Engine!D9 -> 0 | D9: =Engine!E9 -> 0 | E9: =B9 * DSO / 30 -> 0 | F9: =C9 * DSI / 30 -> 0 | G9: =(C9 + D9) * DPO / 30 -> 0 | H9: =E9 + F9 - G9 -> 0 | I9: =H9 - H8 -> 0 | J9: =Engine!M9 -> 0 | K9: =Engine!J9 -> 0 | L9: =Engine!I9 -> 0 | M9: =J9 + K9 - I9 - L9 -> 0 | N9: =N8 + M9 -> 0
A10: 2025-09-01 | B10: =Engine!C10 -> 0 | C10: =Engine!D10 -> 0 | D10: =Engine!E10 -> 0 | E10: =B10 * DSO / 30 -> 0 | F10: =C10 * DSI / 30 -> 0 | G10: =(C10 + D10) * DPO / 30 -> 0 | H10: =E10 + F10 - G10 -> 0 | I10: =H10 - H9 -> 0 | J10: =Engine!M10 -> 0 | K10: =Engine!J10 -> 0 | L10: =Engine!I10 -> 0 | M10: =J10 + K10 - I10 - L10 -> 0 | N10: =N9 + M10 -> 0
A11: 2025-10-01 | B11: =Engine!C11 -> 0 | C11: =Engine!D11 -> 0 | D11: =Engine!E11 -> 0 | E11: =B11 * DSO / 30 -> 0 | F11: =C11 * DSI / 30 -> 0 | G11: =(C11 + D11) * DPO / 30 -> 0 | H11: =E11 + F11 - G11 -> 0 | I11: =H11 - H10 -> 0 | J11: =Engine!M11 -> 0 | K11: =Engine!J11 -> 0 | L11: =Engine!I11 -> 0 | M11: =J11 + K11 - I11 - L11 -> 0 | N11: =N10 + M11 -> 0
A12: 2025-11-01 | B12: =Engine!C12 -> 0 | C12: =Engine!D12 -> 0 | D12: =Engine!E12 -> 0 | E12: =B12 * DSO / 30 -> 0 | F12: =C12 * DSI / 30 -> 0 | G12: =(C12 + D12) * DPO / 30 -> 0 | H12: =E12 + F12 - G12 -> 0 | I12: =H12 - H11 -> 0 | J12: =Engine!M12 -> 0 | K12: =Engine!J12 -> 0 | L12: =Engine!I12 -> 0 | M12: =J12 + K12 - I12 - L12 -> 0 | N12: =N11 + M12 -> 0
A13: 2025-12-01 | B13: =Engine!C13 -> 0 | C13: =Engine!D13 -> 0 | D13: =Engine!E13 -> 0 | E13: =B13 * DSO / 30 -> 0 | F13: =C13 * DSI / 30 -> 0 | G13: =(C13 + D13) * DPO / 30 -> 0 | H13: =E13 + F13 - G13 -> 0 | I13: =H13 - H12 -> 0 | J13: =Engine!M13 -> 0 | K13: =Engine!J13 -> 0 | L13: =Engine!I13 -> 0 | M13: =J13 + K13 - I13 - L13 -> 0 | N13: =N12 + M13 -> 0
A14: 2026-01-01 | B14: =Engine!C14 -> 0 | C14: =Engine!D14 -> 0 | D14: =Engine!E14 -> 0 | E14: =B14 * DSO / 30 -> 0 | F14: =C14 * DSI / 30 -> 0 | G14: =(C14 + D14) * DPO / 30 -> 0 | H14: =E14 + F14 - G14 -> 0 | I14: =H14 - H13 -> 0 | J14: =Engine!M14 -> 0 | K14: =Engine!J14 -> 0 | L14: =Engine!I14 -> 0 | M14: =J14 + K14 - I14 - L14 -> 0 | N14: =N13 + M14 -> 0
... A37: 2027-12-01 | B37: =Engine!C37 -> 0 | C37: =Engine!D37 -> 0 | D37: =Engine!E37 -> 0 | E37: =B37 * DSO / 30 -> 0 | F37: =C37 * DSI / 30 -> 0 | G37: =(C37 + D37) * DPO / 30 -> 0 | H37: =E37 + F37 - G37 -> 0 | I37: =H37 - H36 -> 0 | J37: =Engine!M37 -> 0 | K37: =Engine!J37 -> 0 | L37: =Engine!I37 -> 0 | M37: =J37 + K37 - I37 - L37 -> 0 | N37: =N36 + M37 -> 0

Sheet Sensitivity
A1: Sensitivity: Price Change Impact on Total Revenue
A3: Price Shift | B3: Total Revenue
A4: -0.1 | B4: =SUM(Engine!C:C) * (1 + A4) -> 0
A5: -0.05 | B5: =SUM(Engine!C:C) * (1 + A5) -> 0
A6: 0 | B6: =SUM(Engine!C:C) * (1 + A6) -> 0
A7: 0.05 | B7: =SUM(Engine!C:C) * (1 + A7) -> 0
A8: 0.1 | B8: =SUM(Engine!C:C) * (1 + A8) -> 0

Sheet Checks
A1: Check Name | B1: Status
A2: Revenue Positive | B2: =MIN(Engine!C:C)>0 -> 0
A3: Margins < 100% | B3: =MAX(Engine!H:H/Engine!C:C)<1 -> 0
A4: Cash Balance Positive | B4: =MIN(Working_Capital!N:N)>0 -> 0
